affinda/__init__.py
affinda/__main__.py
affinda/_affinda_api.py
affinda/_configuration.py
affinda/_patch.py
affinda/_vendor.py
affinda/_version.py
affinda/generate_models.py
affinda/py.typed
affinda/token_credential.py
affinda/aio/__init__.py
affinda/aio/_affinda_api.py
affinda/aio/_configuration.py
affinda/aio/_patch.py
affinda/aio/token_credential.py
affinda/aio/operations/__init__.py
affinda/aio/operations/_affinda_api_operations.py
affinda/aio/operations/_patch.py
affinda/models/__init__.py
affinda/models/_affinda_api_enums.py
affinda/models/_models.py
affinda/models/_models_py3.py
affinda/models/_patch.py
affinda/operations/__init__.py
affinda/operations/_affinda_api_operations.py
affinda/operations/_patch.py
affinda-4.28.8.dist-info/licenses/LICENSE
affinda-4.28.8.dist-info/METADATA
affinda-4.28.8.dist-info/WHEEL
affinda-4.28.8.dist-info/top_level.txt
affinda-4.28.8.dist-info/zip-safe
affinda-4.28.8.dist-info/RECORD
